ArWikiCats/__init__.py
ArWikiCats/config.py
ArWikiCats/event_processing.py
ArWikiCats/logging_config.py
ArWikiCats/fix/__init__.py
ArWikiCats/fix/filter_en.py
ArWikiCats/fix/fixlists.py
ArWikiCats/fix/fixtitle.py
ArWikiCats/fix/mv_years.py
ArWikiCats/fix/specific_normalizations.py
ArWikiCats/format_bots/__init__.py
ArWikiCats/format_bots/pf_keys.py
ArWikiCats/format_bots/relation_mapping.py
ArWikiCats/helps/__init__.py
ArWikiCats/helps/jsonl_dump.py
ArWikiCats/helps/len_print.py
ArWikiCats/helps/memory.py
ArWikiCats/jsons/MEN_WOMENS_SINGERS_found.json
ArWikiCats/jsons/SPORT_JOB_VARIANTS_found.json
ArWikiCats/jsons/people_variants_found.json
ArWikiCats/jsons/sport_variants_found.json
ArWikiCats/jsons/_splited_data/P17_2_final_ll_non.json
ArWikiCats/jsons/_splited_data/cities_full_non.json
ArWikiCats/jsons/_splited_data/yy2_non.json
ArWikiCats/jsons/cities/cities_full.json
ArWikiCats/jsons/cities/yy2.json
ArWikiCats/jsons/geography/India_dd.json
ArWikiCats/jsons/geography/New_Keys.json
ArWikiCats/jsons/geography/P17_2_final_ll.json
ArWikiCats/jsons/geography/P17_PP.json
ArWikiCats/jsons/geography/popopo.json
ArWikiCats/jsons/geography/regions.json
ArWikiCats/jsons/geography/regions2.json
ArWikiCats/jsons/geography/us_counties.json
ArWikiCats/jsons/jobs/Jobs_22.json
ArWikiCats/jsons/jobs/Jobs_22_empty.json
ArWikiCats/jsons/jobs/Jobs_players.json
ArWikiCats/jsons/jobs/activists_keys.json
ArWikiCats/jsons/jobs/jobs.json
ArWikiCats/jsons/jobs/jobs_3.json
ArWikiCats/jsons/jobs/jobs_Football_Keys_players.json
ArWikiCats/jsons/jobs/jobs_Men_Womens_PP.json
ArWikiCats/jsons/jobs/jobs_Men_Womens_Singers.json
ArWikiCats/jsons/jobs/singers_tab.json
ArWikiCats/jsons/keys/COMPANY_TYPE_TRANSLATIONS.json
ArWikiCats/jsons/keys/companies_data.json
ArWikiCats/jsons/keys/keys2.json
ArWikiCats/jsons/keys/keys2_py.json
ArWikiCats/jsons/media/Films_key_For_nat.json
ArWikiCats/jsons/media/Films_key_O_multi.json
ArWikiCats/jsons/media/Films_keys_both_new_female_found.json
arwikicats-0.1.0b6.dist-info/METADATA
arwikicats-0.1.0b6.dist-info/WHEEL
arwikicats-0.1.0b6.dist-info/RECORD
