Metadata-Version: 2.4
Name: ArWikiCats
Version: 0.1.0b6
Summary: Arabic Wikipedia Categories Translation Engine
Project-URL: Homepage, https://github.com/MrIbrahem/ArWikiCats
Project-URL: Repository, https://github.com/MrIbrahem/ArWikiCats
Project-URL: Issues, https://github.com/MrIbrahem/ArWikiCats/issues
Author: Ibrahim Qasim
License: MIT
Requires-Python: >=3.10
Requires-Dist: humanize
Requires-Dist: jsonlines
Requires-Dist: psutil
